conftest.py
pybundlr/pybundlr.py
pybundlr-0.1.12.dist-info/METADATA
pybundlr-0.1.12.dist-info/WHEEL
pybundlr-0.1.12.dist-info/licenses/LICENSE
pybundlr-0.1.12.dist-info/RECORD
