Metadata-Version: 2.1
Name: pybundlr
Version: 0.1.12
Summary: Simple py driver for bundlr
Project-URL: Homepage, https://github.com/oceanprotocol/pybundlr
Project-URL: Bug Tracker, https://github.com/oceanprotocol/pybundlr/issues
Author-email: Trent McConaghy <gtrent@gmail.com>
License-File: LICENSE
Classifier: License :: OSI Approved :: MIT License
Classifier: Operating System :: Unix
Classifier: Programming Language :: Python :: 3
Requires-Python: >=3.7
Requires-Dist: enforce-typing==1.0.0.post1
Requires-Dist: pytest
Requires-Dist: requests>=2.21.0
Requires-Dist: web3>=6.0.0
